tf_slice_assign.py
tf_slice_assign-0.0.4.dist-info/LICENSE
tf_slice_assign-0.0.4.dist-info/METADATA
tf_slice_assign-0.0.4.dist-info/WHEEL
tf_slice_assign-0.0.4.dist-info/top_level.txt
tf_slice_assign-0.0.4.dist-info/RECORD
