Metadata-Version: 2.1
Name: tf-slice-assign
Version: 0.0.4
Summary: A package to perform slice assignment in TensorFlow
Home-page: UNKNOWN
Author: Zaccharie Ramzi
Author-email: zaccharie.ramzi@gmail.com
License: UNKNOWN
Download-URL: https://github.com/zaccharieramzi/tf-slice-assign
Keywords: tensorflow
Platform: UNKNOWN
Classifier: Environment :: Console
Classifier: Natural Language :: English
Classifier: Development Status :: 4 - Beta
Classifier: Topic :: Scientific/Engineering :: Artificial Intelligence
Classifier: License :: OSI Approved :: MIT License
Classifier: Programming Language :: Python :: 3
Classifier: Programming Language :: Python :: 3.7
Requires-Python: >=3.5
License-File: LICENSE
Requires-Dist: numpy
Requires-Dist: tensorflow
